bomiot_check-0.3.0.dist-info/METADATA
bomiot_check-0.3.0.dist-info/WHEEL
bomiot_check-0.3.0.dist-info/licenses/LICENSE
bomiot_check/__init__.py
bomiot_check/bomiot_check.cpython-312-darwin.so
bomiot_check-0.3.0.dist-info/RECORD
